annotated_bibliography/__init__.py
annotated_bibliography/helpers.py
annotated_bibliography/make_ann_bib.py
annotated_bibliography/template.html
annotated_bibliography/example/bibtex.bib
annotated_bibliography/example/markdown.md
annotated_bibliography/example/output.html
annotated_bibliography-0.0.4.dist-info/DESCRIPTION.rst
annotated_bibliography-0.0.4.dist-info/METADATA
annotated_bibliography-0.0.4.dist-info/RECORD
annotated_bibliography-0.0.4.dist-info/WHEEL
annotated_bibliography-0.0.4.dist-info/entry_points.txt
annotated_bibliography-0.0.4.dist-info/metadata.json
annotated_bibliography-0.0.4.dist-info/top_level.txt
